{
  "schemaVersion": 1,
  "transports": {
    "protocol-a": {
      "kind": "hid-feature",
      "reportId": 0,
      "writeLength": 65,
      "readLength": 65,
      "stripReportIdOnRead": true
    },
    "protocol-a-receiver": {
      "kind": "hid-feature-proxy",
      "baseTransport": "protocol-a",
      "startCommand": "receiver-start",
      "pollCommand": "receiver-poll",
      "setLengthCommand": "receiver-set-length",
      "readCommand": "receiver-read",
      "sendReady": { "offset": 5, "eq": 1 },
      "readReady": { "offset": 0, "eq": 1 },
      "online": { "offset": 4, "eq": 0 },
      "statusParser": "receiver-status",
      "statusOutput": "receiver",
      "attempts": 20,
      "delayMs": 20
    },
    "am35-direct": {
      "kind": "hid-framed",
      "writeReportId": 6,
      "readReportId": 7,
      "writeLength": 62,
      "readLength": 62,
      "stripReportIdOnRead": true,
      "framePrefix": [],
      "lengthFieldOffset": 0,
      "lengthFieldBytes": 1,
      "typeFieldOffset": 1,
      "typeFieldValue": 0,
      "payloadOffset": 2,
      "requestMatchSlice": [4, 6],
      "responseMatchSlice": [4, 6],
      "endian": "le",
      "readMode": "input-report",
      "readDelayMs": 50,
      "readTimeoutMs": 1000,
      "readRetries": 20
    },
    "am35-receiver": {
      "kind": "hid-framed",
      "writeReportId": 6,
      "readReportId": 7,
      "writeLength": 62,
      "readLength": 62,
      "stripReportIdOnRead": true,
      "framePrefix": [],
      "lengthFieldOffset": 0,
      "lengthFieldBytes": 1,
      "typeFieldOffset": 1,
      "typeFieldValue": 128,
      "payloadOffset": 2,
      "requestMatchSlice": [4, 6],
      "responseMatchSlice": [4, 6],
      "endian": "le",
      "readMode": "input-report",
      "readDelayMs": 50,
      "readTimeoutMs": 1000,
      "readRetries": 20
    }
  }
}
